data/__init__.py
data/main.py
pylister/__init__.py
pylister/main.py
pylister-1.0.3.dist-info/LICENSE
pylister-1.0.3.dist-info/METADATA
pylister-1.0.3.dist-info/WHEEL
pylister-1.0.3.dist-info/entry_points.txt
pylister-1.0.3.dist-info/top_level.txt
pylister-1.0.3.dist-info/RECORD
