Metadata-Version: 2.1
Name: pylister
Version: 1.0.3
Author: recleun
Keywords: cli,tool,task-management
License-File: LICENSE
Requires-Dist: Click
